wechaty_grpc/__init__.py
wechaty_grpc/google/__init__.py
wechaty_grpc/google/api/__init__.py
wechaty_grpc/grpc/__init__.py
wechaty_grpc/grpc/gateway/__init__.py
wechaty_grpc/grpc/gateway/protoc_gen_openapiv2/__init__.py
wechaty_grpc/grpc/gateway/protoc_gen_openapiv2/options/__init__.py
wechaty_grpc/wechaty/__init__.py
wechaty_grpc/wechaty/puppet/__init__.py
wechaty_grpc-0.20.19.dist-info/METADATA
wechaty_grpc-0.20.19.dist-info/WHEEL
wechaty_grpc-0.20.19.dist-info/top_level.txt
wechaty_grpc-0.20.19.dist-info/RECORD
