Metadata-Version: 2.1
Name: wechaty-grpc
Version: 0.20.19
Summary: Wechaty Puppet Service gRPC API
Home-page: https://github.com/wechaty/grpc
Author: Huan LI (李卓桓)
Author-email: zixia@zixia.net
License: Apache-2.0
Platform: UNKNOWN
Classifier: Programming Language :: Python :: 3.7
Classifier: License :: OSI Approved :: Apache Software License
Classifier: Operating System :: OS Independent
Requires-Dist: betterproto
Requires-Dist: grpclib
